{
  "project_info": {
    "project_number": "92243706550",
    "project_id": "english-with-lidia-for-android",
    "storage_bucket": "english-with-lidia-for-android.firebasestorage.app"
  },
  "client": [
    {
      "client_info": {
        "mobilesdk_app_id": "1:92243706550:android:957477a9dcc82329b41c17",
        "android_client_info": {
          "package_name": "com.d4rk.englishwithlidia.plus"
        }
      },
      "oauth_client": [],
      "api_key": [
        {
          "current_key": "AIzaSyBaMiU-hm902iB9wxWrYa-d7F_0xuIJrpY"
        }
      ],
      "services": {
        "appinvite_service": {
          "other_platform_oauth_client": []
        }
      },
      "admob_app_id": "ca-app-pub-5294151573817700~8003610653"
    }
  ],
  "configuration_version": "1"
}